topomodelx/__init__.py
topomodelx/base/__init__.py
topomodelx/base/aggregation.py
topomodelx/base/conv.py
topomodelx/base/message_passing.py
topomodelx/nn/__init__.py
topomodelx/nn/cell/can.py
topomodelx/nn/cell/can_layer.py
topomodelx/nn/cell/ccxn.py
topomodelx/nn/cell/ccxn_layer.py
topomodelx/nn/cell/cwn.py
topomodelx/nn/cell/cwn_layer.py
topomodelx/nn/combinatorial/hmc.py
topomodelx/nn/combinatorial/hmc_layer.py
topomodelx/nn/hypergraph/allset.py
topomodelx/nn/hypergraph/allset_layer.py
topomodelx/nn/hypergraph/allset_transformer.py
topomodelx/nn/hypergraph/allset_transformer_layer.py
topomodelx/nn/hypergraph/dhgcn.py
topomodelx/nn/hypergraph/dhgcn_layer.py
topomodelx/nn/hypergraph/hmpnn.py
topomodelx/nn/hypergraph/hmpnn_layer.py
topomodelx/nn/hypergraph/hnhn.py
topomodelx/nn/hypergraph/hnhn_layer.py
topomodelx/nn/hypergraph/hypergat.py
topomodelx/nn/hypergraph/hypergat_layer.py
topomodelx/nn/hypergraph/hypersage.py
topomodelx/nn/hypergraph/hypersage_layer.py
topomodelx/nn/hypergraph/unigcn.py
topomodelx/nn/hypergraph/unigcn_layer.py
topomodelx/nn/hypergraph/unigcnii.py
topomodelx/nn/hypergraph/unigcnii_layer.py
topomodelx/nn/hypergraph/unigin.py
topomodelx/nn/hypergraph/unigin_layer.py
topomodelx/nn/hypergraph/unisage.py
topomodelx/nn/hypergraph/unisage_layer.py
topomodelx/nn/simplicial/__init__.py
topomodelx/nn/simplicial/dist2cycle.py
topomodelx/nn/simplicial/dist2cycle_layer.py
topomodelx/nn/simplicial/hsn.py
topomodelx/nn/simplicial/hsn_layer.py
topomodelx/nn/simplicial/san.py
topomodelx/nn/simplicial/san_layer.py
topomodelx/nn/simplicial/sca_cmps.py
topomodelx/nn/simplicial/sca_cmps_layer.py
topomodelx/nn/simplicial/sccn.py
topomodelx/nn/simplicial/sccn_layer.py
topomodelx/nn/simplicial/sccnn.py
topomodelx/nn/simplicial/sccnn_layer.py
topomodelx/nn/simplicial/scconv.py
topomodelx/nn/simplicial/scconv_layer.py
topomodelx/nn/simplicial/scn2.py
topomodelx/nn/simplicial/scn2_layer.py
topomodelx/nn/simplicial/scnn.py
topomodelx/nn/simplicial/scnn_layer.py
TopoModelX-0.0.1.dist-info/LICENSE
TopoModelX-0.0.1.dist-info/METADATA
TopoModelX-0.0.1.dist-info/WHEEL
TopoModelX-0.0.1.dist-info/top_level.txt
TopoModelX-0.0.1.dist-info/RECORD
