Metadata-Version: 2.1
Name: TopoModelX
Version: 0.0.1
Summary: Topological Deep Learning
Author-email: PyT-Team Authors <mustafahajij@gmail.com>
Project-URL: homepage, https://github.com/pyt-team/TopoModelX
Project-URL: repository, https://github.com/pyt-team/TopoModelX
Project-URL: documentation, https://pyt-team.github.io/TopoModelX
Project-URL: issues, https://github.com/pyt-team/TopoModelX/issues
Classifier: License :: OSI Approved :: MIT License
Classifier: Development Status :: 4 - Beta
Classifier: Intended Audience :: Science/Research
Classifier: Topic :: Scientific/Engineering
Classifier: Topic :: Scientific/Engineering :: Mathematics
Classifier: Topic :: Scientific/Engineering :: Artificial Intelligence
Classifier: Natural Language :: English
Classifier: Programming Language :: Python :: 3
Classifier: Programming Language :: Python :: 3.10
Classifier: Programming Language :: Python :: 3.11
Requires-Python: >=3.10
License-File: LICENSE
Requires-Dist: tqdm
Requires-Dist: numpy<2
Requires-Dist: scipy
Requires-Dist: requests
Requires-Dist: scikit-learn
Requires-Dist: matplotlib
Requires-Dist: networkx
Requires-Dist: gudhi
Requires-Dist: pandas
Requires-Dist: pyg-nightly
Requires-Dist: toponetx
Provides-Extra: all
Requires-Dist: TopoModelX[dev,doc]; extra == "all"
Provides-Extra: dev
Requires-Dist: TopoModelX[lint,test]; extra == "dev"
Provides-Extra: doc
Requires-Dist: hypernetx; extra == "doc"
Requires-Dist: jupyter; extra == "doc"
Requires-Dist: nbsphinx; extra == "doc"
Requires-Dist: nbsphinx-link; extra == "doc"
Requires-Dist: numpydoc; extra == "doc"
Requires-Dist: sphinx; extra == "doc"
Requires-Dist: sphinx-gallery; extra == "doc"
Requires-Dist: pydata-sphinx-theme; extra == "doc"
Provides-Extra: lint
Requires-Dist: pre-commit; extra == "lint"
Requires-Dist: ruff; extra == "lint"
Provides-Extra: test
Requires-Dist: pytest; extra == "test"
Requires-Dist: pytest-cov; extra == "test"
Requires-Dist: coverage; extra == "test"
Requires-Dist: jupyter; extra == "test"
Requires-Dist: mypy; extra == "test"
Requires-Dist: pytest-xdist; extra == "test"
Requires-Dist: pytest-split; extra == "test"
